NotifPy/EmailNotif.py
NotifPy/SMSNotif.py
NotifPy/__init__.py
NotifPy-0.0.4.dist-info/LICENSE
NotifPy-0.0.4.dist-info/METADATA
NotifPy-0.0.4.dist-info/WHEEL
NotifPy-0.0.4.dist-info/top_level.txt
NotifPy-0.0.4.dist-info/RECORD
