Metadata-Version: 2.1
Name: NotifPy
Version: 0.0.4
Summary: NotifPy is here to send alert, notification and promotion related email and SMS
Home-page: https://github.com/ArianFotouhi
Author: Arian
Author-email: arianspiderman@yahoo.com
Classifier: Programming Language :: Python :: 3
Classifier: License :: OSI Approved :: MIT License
Classifier: Operating System :: OS Independent
Requires-Python: >=3.7
License-File: LICENSE
